aiosendspin_sounddevice/__init__.py
aiosendspin_sounddevice/audio.py
aiosendspin_sounddevice/audio_device.py
aiosendspin_sounddevice/client.py
aiosendspin_sounddevice/discovery.py
aiosendspin_sounddevice-0.3.0.dist-info/licenses/LICENSE
aiosendspin_sounddevice-0.3.0.dist-info/METADATA
aiosendspin_sounddevice-0.3.0.dist-info/WHEEL
aiosendspin_sounddevice-0.3.0.dist-info/top_level.txt
aiosendspin_sounddevice-0.3.0.dist-info/RECORD
