Metadata-Version: 2.4
Name: aiosendspin-sounddevice
Version: 0.3.0
Summary: Python library wrapping aiosendspin and sounddevice for programmatic audio playback
Author-email: Benjamin Hesse <100107950+behesse@users.noreply.github.com>
License-Expression: Apache-2.0
Classifier: Development Status :: 3 - Alpha
Classifier: Intended Audience :: Developers
Classifier: Programming Language :: Python :: 3
Classifier: Programming Language :: Python :: 3.12
Classifier: Programming Language :: Python :: 3.13
Requires-Python: >=3.12
License-File: LICENSE
Requires-Dist: aiosendspin>=1.2.0
Requires-Dist: numpy>=1.24.0
Requires-Dist: sounddevice>=0.4.6
Requires-Dist: zeroconf>=0.131.0
Provides-Extra: test
Requires-Dist: pytest>=7.0.0; extra == "test"
Requires-Dist: pytest-asyncio>=0.21.0; extra == "test"
Provides-Extra: dev
Requires-Dist: ruff>=0.1.0; extra == "dev"
Requires-Dist: sphinx>=7.0.0; extra == "dev"
Requires-Dist: sphinx-rtd-theme>=2.0.0; extra == "dev"
Dynamic: license-file
